ATIVIDADES-PRATICAS/ATIVIDADE-PRATICA-6/TAREFA-3/ff_t.v
module ff_t (clk, T, clear, q);

    input wire clk, T, clear;
    output reg q;

    always @(posedge clk) begin
        if (clear)
            q = 0;
        else 
            if (T)
                q = ~q;
            else
                q = q;
    end

endmodule

ATIVIDADES-PRATICAS/ATIVIDADE-PRATICA-6/TAREFA-3/contador_sincrono_crescente_4bits.v
`include "ff_t.v"

module contador_sincrono_crescente_4bits (clk, T, clear, q);
    output [3:0] q;
    input clk, T, clear;

    wire variavel1, variavel2;

    ff_t ff_t_1 (clk, T, clear, q[0]);
    ff_t ff_t_2 (clk, q[0], clear, q[1]);
    
    assign variavel1 = q[0] & q[1];
    ff_t ff_t_3 (clk, variavel1, clear, q[2]);
    
    assign variavel2 = variavel1 & q[2];
    ff_t ff_t_4 (clk, variavel2, clear, q[3]);

endmodule

ATIVIDADES-PRATICAS/ATIVIDADE-PRATICA-6/TAREFA-3/contador_sincrono_crescente_4bits_tb.v
`timescale 1ns/1ns
`include "contador_sincrono_crescente_4bits.v"

module contador_sincrono_crescente_4bits_tb;

    reg clk, T, clear;
    wire [3:0] q;

    contador_sincrono_crescente_4bits uut(clk, T, clear, q);

    initial begin
        $dumpfile("contador_sincrono_crescente_4bits.vcd");
        $dumpvars(0, contador_sincrono_crescente_4bits_tb);


        {clear,T} = 2'b11; #20; 

        {clear,T} = 2'b01; #20; 
        {clear,T} = 2'b01; #20; 
        {clear,T} = 2'b01; #20;         
        {clear,T} = 2'b01; #20; 
        
        {clear,T} = 2'b01; #20; 
        {clear,T} = 2'b01; #20; 
        {clear,T} = 2'b01; #20;         
        {clear,T} = 2'b01; #20; 
        
        {clear,T} = 2'b01; #20; 
        {clear,T} = 2'b01; #20; 
        {clear,T} = 2'b01; #20;         
        {clear,T} = 2'b01; #20; 
        
        {clear,T} = 2'b01; #20; 
        {clear,T} = 2'b01; #20; 
        {clear,T} = 2'b01; #20;         
        {clear,T} = 2'b01; #20; 
        
        $display("Teste completo");
        $finish;
    end

    initial begin
        clk = 0;
        forever #10 clk = ~clk ;
    end

endmodule

ATIVIDADES-PRATICAS/ATIVIDADE-PRATICA-6/TAREFA-3/contador_sincrono_crescente_4bits.vcd
$date
	Sun Nov 17 17:14:44 2024
$end
$version
	Icarus Verilog
$end
$timescale
	1ns
$end
$scope module contador_sincrono_crescente_4bits_tb $end
$var wire 4 ! q [3:0] $end
$var reg 1 " T $end
$var reg 1 # clear $end
$var reg 1 $ clk $end
$scope module uut $end
$var wire 1 " T $end
$var wire 1 # clear $end
$var wire 1 $ clk $end
$var wire 1 % variavel1 $end
$var wire 1 & variavel2 $end
$var wire 4 ' q [3:0] $end
$scope module ff_t_1 $end
$var wire 1 " T $end
$var wire 1 # clear $end
$var wire 1 $ clk $end
$var reg 1 ( q $end
$upscope $end
$scope module ff_t_2 $end
$var wire 1 ) T $end
$var wire 1 # clear $end
$var wire 1 $ clk $end
$var reg 1 * q $end
$upscope $end
$scope module ff_t_3 $end
$var wire 1 % T $end
$var wire 1 # clear $end
$var wire 1 $ clk $end
$var reg 1 + q $end
$upscope $end
$scope module ff_t_4 $end
$var wire 1 & T $end
$var wire 1 # clear $end
$var wire 1 $ clk $end
$var reg 1 , q $end
$upscope $end
$upscope $end
$upscope $end
$enddefinitions $end
$comment Show the parameter values. $end
$dumpall
$end
#0
$dumpvars
x,
x+
x*
x)
x(
bx '
x&
x%
0$
1#
1"
bx !
$end
#10
0%
0&
0)
0(
0*
0+
b0 !
b0 '
0,
1$
#20
0$
0#
#30
1)
b1 !
b1 '
1(
1$
#40
0$
#50
0)
0(
b10 !
b10 '
1*
1$
#60
0$
#70
1%
1)
b11 !
b11 '
1(
1$
#80
0$
#90
0%
0&
0)
0(
0*
b100 !
b100 '
1+
1$
#100
0$
#110
1)
b101 !
b101 '
1(
1$
#120
0$
#130
0)
0(
b110 !
b110 '
1*
1$
#140
0$
#150
1&
1%
1)
b111 !
b111 '
1(
1$
#160
0$
#170
0%
0&
0)
0(
0*
0+
b1000 !
b1000 '
1,
1$
#180
0$
#190
1)
b1001 !
b1001 '
1(
1$
#200
0$
#210
0)
0(
b1010 !
b1010 '
1*
1$
#220
0$
#230
1%
1)
b1011 !
b1011 '
1(
1$
#240
0$
#250
0%
0&
0)
0(
0*
b1100 !
b1100 '
1+
1$
#260
0$
#270
1)
b1101 !
b1101 '
1(
1$
#280
0$
#290
0)
0(
b1110 !
b1110 '
1*
1$
#300
0$
#310
1&
1%
1)
b1111 !
b1111 '
1(
1$
#320
0$
#330
0%
0&
0)
0(
0*
0+
b0 !
b0 '
0,
1$
#340
0$
#350
1)
b1 !
b1 '
1(
1$
#360
0$
#370
0)
0(
b10 !
b10 '
1*
1$
#380
0$
#390
1%
1)
b11 !
b11 '
1(
1$
#400
0$
#410
0%
0&
0)
0(
0*
b100 !
b100 '
1+
1$
#420
0$
#430
1)
b101 !
b101 '
1(
1$
#440
0$
#450
0)
0(
b110 !
b110 '
1*
1$
#460
0$
#470
1&
1%
1)
b111 !
b111 '
1(
1$
#480
0$
#490
0%
0&
0)
0(
0*
0+
b1000 !
b1000 '
1,
1$
#500
0$
#510
1)
b1001 !
b1001 '
1(
1$
#520
0$
#530
0)
0(
b1010 !
b1010 '
1*
1$
#540
0$
#550
1%
1)
b1011 !
b1011 '
1(
1$
#560
0$
#570
0%
0&
0)
0(
0*
b1100 !
b1100 '
1+
1$
#580
0$
#590
1)
b1101 !
b1101 '
1(
1$
#600
0$
#610
0)
0(
b1110 !
b1110 '
1*
1$
#620
0$
#630
1&
1%
1)
b1111 !
b1111 '
1(
1$
#640
0$
#650
0%
0&
0)
0(
0*
0+
b0 !
b0 '
0,
1$
#660
0$
#670
1)
b1 !
b1 '
1(
1$
#680
0$
#690
0)
0(
b10 !
b10 '
1*
1$
#700
0$
#710
1%
1)
b11 !
b11 '
1(
1$
#720
0$
#730
0%
0&
0)
0(
0*
b100 !
b100 '
1+
1$
#740
0$
#750
1)
b101 !
b101 '
1(
1$
#760
0$
#770
0)
0(
b110 !
b110 '
1*
1$
#780
0$
#790
1&
1%
1)
b111 !
b111 '
1(
1$
#800
0$
#810
0%
0&
0)
0(
0*
0+
b1000 !
b1000 '
1,
1$
#820
0$
#830
1)
b1001 !
b1001 '
1(
1$
#840
0$
#850
0)
0(
b1010 !
b1010 '
1*
1$
#860
0$
#870
1%
1)
b1011 !
b1011 '
1(
1$
#880
0$
#890
0%
0&
0)
0(
0*
b1100 !
b1100 '
1+
1$
#900
0$
#910
1)
b1101 !
b1101 '
1(
1$
#920
0$
#930
0)
0(
b1110 !
b1110 '
1*
1$
#940
0$
#950
1&
1%
1)
b1111 !
b1111 '
1(
1$
#960
0$
#970
0%
0&
0)
0(
0*
0+
b0 !
b0 '
0,
1$
