PCG/ula8its/comparador8bits.v
module comparador8bits (entradaA, entradaB, codigoComparacao, saida9Bits);
    input [7:0] entradaA, entradaB;
    input [3:0] codigoComparacao;

    output reg [8:0] saida9Bits;

    integer i;

    always @(*) begin
        for (i = 0; i < 8; i = i + 1) begin
            case (codigoComparacao)
                4'b111: // NOT
                    if (entradaA[i] == entradaB[i])
                        if (entradaA[i]) 
                            saida9Bits[i] = 0;
                        else
                            saida9Bits[i] = 1;
                    else
                        saida9Bits[i] = ~entradaA[i];
                4'b1000: // AND
                    saida9Bits[i] = entradaA[i] & entradaB[i];
                4'b1001: // OR
                    saida9Bits[i] = entradaA[i] | entradaB[i];
                4'b1010: //XOR
                    saida9Bits[i] = entradaA[i] ^ entradaB[i];
                4'b1011: // XNOR
                    saida9Bits[i] = entradaA[i] ~^ entradaB[i];
                default: saida9Bits[i] = 0;
            endcase
        end
        saida9Bits[8] = 0; // Bit extra configurado para 0
    end
endmodule

ATIVIDADES-PRATICAS/ATIVIDADE-PRATICA-4/somador e subtrator de n bits/subtrator/subtrator_completo.v
module subtrator_completo (A, B, CIN, S, COUT);

    input A, B, CIN;
    output S, COUT;

    assign S = A ^ B ^ CIN; 
    assign COUT = ~A & B | ~A & CIN | B & CIN;

endmodule

ATIVIDADES-PRATICAS/ATIVIDADE-PRATICA-4/somador e subtrator de n bits/subtrator/meio_subtrator.v
module meio_subtrator (A, B, S, C);

    input A, B;
    output S, C;

    assign S = A ^ B;
    assign C = ~A & B;

endmodule

ATIVIDADES-PRATICAS/ATIVIDADE-PRATICA-4/somador e subtrator de n bits/subtrator/subtrator8bits.v
`include"subtrator_completo.v"
`include"meio_subtrator.v"

module subtrator8bits (A, B, S);

    input [7:0] A, B;
    output [8:0] S;
    wire [6:0] C;

    meio_subtrator unidade1 (A[0], B[0], S[0], C[0]);
    subtrator_completo unidade2 (A[1], B[1], C[0], S[1], C[1]);
    subtrator_completo unidade3 (A[2], B[2], C[1], S[2], C[2]);
    subtrator_completo unidade4 (A[3], B[3], C[2], S[3], C[3]);
    subtrator_completo unidade5 (A[4], B[4], C[3], S[4], C[4]);
    subtrator_completo unidade6 (A[5], B[5], C[4], S[5], C[5]);
    subtrator_completo unidade7 (A[6], B[6], C[5], S[6], C[6]);
    subtrator_completo unidade8 (A[7], B[7], C[6], S[7], S[8]);

endmodule

ATIVIDADES-PRATICAS/ATIVIDADE-PRATICA-4/somador e subtrator de n bits/somador/somador_completo.v
module somador_completo (A, B, CIN, S, COUT);

    input A, B, CIN;
    output S, COUT;

    assign S = A ^ B ^ CIN; 
    assign COUT = B & CIN | A & CIN | A & B;

endmodule

PCG/ula8its/meio_somador.v
module meio_somador (A, B, S, C);

    input A, B;
    output S, C;

    assign S = A ^ B; 
    assign C = A & B;

endmodule

ATIVIDADES-PRATICAS/ATIVIDADE-PRATICA-4/somador e subtrator de n bits/somador/somador8bits.v
`include"somador_completo.v"
`include"meio_somador.v"

module somador8bits (A, B, S);

    input [7:0] A, B;
    output [8:0] S;
    wire [6:0] C;

    meio_somador unidade1 (A[0], B[0], S[0], C[0]);
    somador_completo unidade2 (A[1], B[1], C[0], S[1], C[1]);
    somador_completo unidade3 (A[2], B[2], C[1], S[2], C[2]);
    somador_completo unidade4 (A[3], B[3], C[2], S[3], C[3]);
    somador_completo unidade5 (A[4], B[4], C[3], S[4], C[4]);
    somador_completo unidade6 (A[5], B[5], C[4], S[5], C[5]);
    somador_completo unidade7 (A[6], B[6], C[5], S[6], C[6]);
    somador_completo unidade8 (A[7], B[7], C[6], S[7], S[8]);

endmodule

PCG/ula8its/ula.v
`include "somador8bits.v"
`include "subtrator8bits.v"
`include "comparador8bits.v"

module ula (entradaA8Bits, entradaB8Bits, opCode, clock, saida9Bits);
    input [7:0] entradaA8Bits, entradaB8Bits;
    input [3:0] opCode;
    input clock;

    output reg [8:0] saida9Bits;

    wire [8:0] resultado_soma;
    wire [8:0] resultado_subtracao;
    wire [8:0] resultado_comparacao;

    somador8bits somador_inst(
        .A(entradaA8Bits),
        .B(entradaB8Bits),
        .S(resultado_soma)
    );

    subtrator8bits subtrator_inst(
        .A(entradaA8Bits),
        .B(entradaB8Bits),
        .S(resultado_subtracao)
    );

    comparador8bits comparador8bits_inst(
        .entradaA(entradaA8Bits),
        .entradaB(entradaB8Bits),
        .codigoComparacao(opCode),
        .saida9Bits(resultado_comparacao)
    );

    always @(posedge clock) begin
        case (opCode)
            4'b0: // SOMA
                saida9Bits = resultado_soma;
            4'b1: // SUBTRAÇÃO
                saida9Bits = resultado_subtracao;
            4'b10: // MAIOR QUE >
                saida9Bits = entradaA8Bits > entradaB8Bits;
            4'b11: // MENOR QUE <
                saida9Bits = entradaA8Bits < entradaB8Bits;
            4'b100: // MAIOR OU IGUAL >= 
                saida9Bits = entradaA8Bits >= entradaB8Bits;
            4'b101: // MENOR OU IGUAL <=
                saida9Bits = entradaA8Bits <= entradaB8Bits;
            4'b110: // IGUAL
                saida9Bits = entradaA8Bits == entradaB8Bits;
            4'b111: // NOT ! 
                saida9Bits = resultado_comparacao;
            4'b1000: // AND
                saida9Bits = resultado_comparacao;
            4'b1001: // OR
                saida9Bits = resultado_comparacao;
            4'b1010: // XOR
                saida9Bits = resultado_comparacao;
            4'b1011: // XNOR
                saida9Bits = resultado_comparacao;
            default:  saida9Bits = 9'bx;
        endcase
    end

endmodule

PCG/ula8its/ula_tb.v
`timescale 1ns/1ns
`include "ula.v"

module ula_tb;

    reg [7:0] entradaA8Bits, entradaB8Bits;
    reg [3:0] opCode;
    reg clock;

    wire [8:0] saida9Bits;
    
    ula uut(entradaA8Bits, entradaB8Bits, opCode, clock, saida9Bits);

    initial begin
        $dumpfile("ula_tb.vcd");
        $dumpvars(0, ula_tb);

        // TESTE SOMA, 9 + 20 = 29
        opCode = 4'b0; #10;
        entradaA8Bits = 8'b1001;
        entradaB8Bits = 8'b10100; #10;

        // TESTE SOMA, 255 + 255 = 510
        entradaA8Bits = 8'b11111111;
        entradaB8Bits = 8'b11111111; #10;

        // ~~~~~~~~~~~~~~~~~~~~~~~~~~~~~~~~~~~~~~~~~~~~~~~~~~~~~~~~~~~~~~~~~~~~~~~~~~~~~~~~~~~~~~~~~~~~~~~~~~~~~ //

        // TESTE SUBTRACAO, 25 - 5 = 20
        opCode = 4'b1; #10;
        entradaA8Bits = 8'b11001;
        entradaB8Bits = 8'b101; #10;

        // TESTE SUBTRACAO, 255 - 255 = 0
        entradaA8Bits = 8'b11111111;
        entradaB8Bits = 8'b11111111; #10;

        // ~~~~~~~~~~~~~~~~~~~~~~~~~~~~~~~~~~~~~~~~~~~~~~~~~~~~~~~~~~~~~~~~~~~~~~~~~~~~~~~~~~~~~~~~~~~~~~~~~~~~~ //

        // TESTE MAIOR QUE, 80 > 70 = TRUE
        opCode = 4'b10;
        entradaA8Bits = 8'b1010000;
        entradaB8Bits = 8'b1000110; #10;

        // TESTE MAIOR QUE, 100 > 120 = FALSE
        entradaA8Bits = 8'b1100100;
        entradaB8Bits = 8'b1111000; #10;

        // ~~~~~~~~~~~~~~~~~~~~~~~~~~~~~~~~~~~~~~~~~~~~~~~~~~~~~~~~~~~~~~~~~~~~~~~~~~~~~~~~~~~~~~~~~~~~~~~~~~~~~ //

        // TESTE MENOR QUE, 150 < 220 = TRUE
        opCode = 4'b11;
        entradaA8Bits = 8'b10010110;
        entradaB8Bits = 8'b11011100; #10;

        // TESTE MENOR QUE, 189 < 110 = FALSE
        entradaA8Bits = 8'b10111101;
        entradaB8Bits = 8'b1101110; #10;

        // ~~~~~~~~~~~~~~~~~~~~~~~~~~~~~~~~~~~~~~~~~~~~~~~~~~~~~~~~~~~~~~~~~~~~~~~~~~~~~~~~~~~~~~~~~~~~~~~~~~~~~ //

        // TESTE MAIOR OU IGUAL, 2 >= 2 = TRUE
        opCode = 4'b100;
        entradaA8Bits = 8'b10;
        entradaB8Bits = 8'b10; #10;

        // TESTE MAIOR OU IGUAL, 45 >= 30 = TRUE
        opCode = 4'b100;
        entradaA8Bits = 8'b101101;
        entradaB8Bits = 8'b11110; #10;

        // TESTE MAIOR OU IGUAL, 90 >= 150 = FALSE
        opCode = 4'b100;
        entradaA8Bits = 8'b1011010;
        entradaB8Bits = 8'b10010110; #10;

        // ~~~~~~~~~~~~~~~~~~~~~~~~~~~~~~~~~~~~~~~~~~~~~~~~~~~~~~~~~~~~~~~~~~~~~~~~~~~~~~~~~~~~~~~~~~~~~~~~~~~~~ //

        // TESTE MENOR OU IGUAL, 30 <= 30 = TRUE
        opCode = 4'b101;
        entradaA8Bits = 8'b11110;
        entradaB8Bits = 8'b11110; #10;

        // TESTE MENOR OU IGUAL, 60 <= 120 = TRUE (primeiro número menor que o segundo)
        entradaA8Bits = 8'b111100;
        entradaB8Bits = 8'b1111000; #10;

        // TESTE MENOR OU IGUAL, 200 <= 100 = FALSE (primeiro número maior que o segundo)
        entradaA8Bits = 8'b11001000;
        entradaB8Bits = 8'b1100100; #10;

        // ~~~~~~~~~~~~~~~~~~~~~~~~~~~~~~~~~~~~~~~~~~~~~~~~~~~~~~~~~~~~~~~~~~~~~~~~~~~~~~~~~~~~~~~~~~~~~~~~~~~~~ //

        // TESTE IGUAL, 50 == 50 = TRUE
        opCode = 4'b110;
        entradaA8Bits = 8'b110010;
        entradaB8Bits = 8'b110010; #10;

        // TESTE IGUAL, 100 == 24 = FALSE
        entradaA8Bits = 8'b1100100;
        entradaB8Bits = 8'b11000;  #10;

        // TESTE IGUAL, 30 == 21 = FALSE
        entradaA8Bits = 8'b11110;
        entradaB8Bits = 8'b10101; #10;

        // ~~~~~~~~~~~~~~~~~~~~~~~~~~~~~~~~~~~~~~~~~~~~~~~~~~~~~~~~~~~~~~~~~~~~~~~~~~~~~~~~~~~~~~~~~~~~~~~~~~~~~ //

        // TESTE NOT, 1111 1111 COM 1111 1111 = 0000 0000
        opCode = 4'b111;
        entradaA8Bits = 8'b11111111;
        entradaB8Bits = 8'b11111111; #10;

        // TESTE NOT, 0000 0000 COM 0000 0000 = 1111 1111
        entradaA8Bits = 8'b0;
        entradaB8Bits = 8'b0; #10;

        // TESTE NOT, 0101 0101 COM 0101 0101 = 10101010
        entradaA8Bits = 8'b01010101;
        entradaB8Bits = 8'b01010101; #10;

        // TESTE NOT, 1010 1010 COM 1010 1010 = 01010101
        entradaA8Bits = 8'b10101010;
        entradaB8Bits = 8'b10101010; #10;

        // TESTE NOT, 1100 0011 COM 1100 0011 = 00111100
        entradaA8Bits = 8'b11000011;
        entradaB8Bits = 8'b11000011; #10;

        // TESTE NOT, 0011 1100 COM 0011 1100 = 11000011
        entradaA8Bits = 8'b111100;
        entradaB8Bits = 8'b111100; #10;

        // ~~~~~~~~~~~~~~~~~~~~~~~~~~~~~~~~~~~~~~~~~~~~~~~~~~~~~~~~~~~~~~~~~~~~~~~~~~~~~~~~~~~~~~~~~~~~~~~~~~~~~ //

        // TESTE AND, 1111 1111 COM 1111 1111 = 11111111
        opCode = 4'b1000;
        entradaA8Bits = 8'b11111111;
        entradaB8Bits = 8'b11111111; #10;        

        // TESTE AND, 0000 0000 COM 0000 0000 = 00000000
        entradaA8Bits = 8'b0;
        entradaB8Bits = 8'b0; #10;

        // TESTE AND, 1010 1010 COM 1010 1010 = 10101010
        entradaA8Bits = 8'b10101010;
        entradaB8Bits = 8'b10101010; #10;

        // TESTE AND, 1010 1010 COM 0101 0101 = 00000000
        entradaA8Bits = 8'b10101010;
        entradaB8Bits = 8'b01010101; #10;

        // ~~~~~~~~~~~~~~~~~~~~~~~~~~~~~~~~~~~~~~~~~~~~~~~~~~~~~~~~~~~~~~~~~~~~~~~~~~~~~~~~~~~~~~~~~~~~~~~~~~~~~ //

        // TESTE OR, 1111 1111 COM 1111 1111 = 11111111
        opCode = 4'b1001;
        entradaA8Bits = 8'b11111111;
        entradaB8Bits = 8'b11111111; #10;

        // TESTE OR, 1010 1010 COM 0101 0101 = 11111111
        entradaA8Bits = 8'b10101010;
        entradaB8Bits = 8'b01010101; #10;

        // TESTE OR, 0000 0000 COM 0000 0000 = 00000000
        entradaA8Bits = 8'b0;
        entradaB8Bits = 8'b0; #10;

        // TESTE OR, 1010 1010 COM 1010 1010 = 10101010
        entradaA8Bits = 8'b10101010;
        entradaB8Bits = 8'b10101010; #10;

        // ~~~~~~~~~~~~~~~~~~~~~~~~~~~~~~~~~~~~~~~~~~~~~~~~~~~~~~~~~~~~~~~~~~~~~~~~~~~~~~~~~~~~~~~~~~~~~~~~~~~~~ //

        // TESTE XOR, 1111 1111 COM 1111 1111 = 00000000
        opCode = 4'b1010;
        entradaA8Bits = 8'b11111111;
        entradaB8Bits = 8'b11111111; #10;

        // TESTE XOR, 0000 0000 COM 0000 0000 = 00000000
        entradaA8Bits = 8'b0;
        entradaB8Bits = 8'b0; #10;

        // TESTE XOR, 1010 1010 COM 0101 0101 = 11111111
        entradaA8Bits = 8'b10101010;
        entradaB8Bits = 8'b01010101; #10;

        // TESTE XOR, 1010 1010 COM 1010 1010 = 00000000
        entradaA8Bits = 8'b10101010;
        entradaB8Bits = 8'b10101010; #10;

        // ~~~~~~~~~~~~~~~~~~~~~~~~~~~~~~~~~~~~~~~~~~~~~~~~~~~~~~~~~~~~~~~~~~~~~~~~~~~~~~~~~~~~~~~~~~~~~~~~~~~~~ //

        // TESTE XNOR, 1111 1111 COM 1111 1111 = 11111111
        opCode = 4'b1011;
        entradaA8Bits = 8'b11111111;
        entradaB8Bits = 8'b11111111; #10;

        // TESTE XNOR, 0000 0000 COM 0000 0000 = 11111111
        entradaA8Bits = 8'b0;
        entradaB8Bits = 8'b0; #10;

        // TESTE XNOR, 1010 1010 COM 0101 0101 = 00000000
        entradaA8Bits = 8'b10101010;
        entradaB8Bits = 8'b01010101; #10;

        // TESTE XNOR, 1010 1010 COM 1010 1010 = 11111111
        entradaA8Bits = 8'b10101010;
        entradaB8Bits = 8'b10101010; #10;

        $display("Teste completo");
        $finish;
    end

    initial begin
        clock = 0;
        forever #5 clock = ~clock ;
    end

endmodule

PCG/ula8its/ula_tb.vcd
$date
	Tue Nov 19 01:06:32 2024
$end
$version
	Icarus Verilog
$end
$timescale
	1ns
$end
$scope module ula_tb $end
$var wire 9 ! saida9Bits [8:0] $end
$var reg 1 " clock $end
$var reg 8 # entradaA8Bits [7:0] $end
$var reg 8 $ entradaB8Bits [7:0] $end
$var reg 4 % opCode [3:0] $end
$scope module uut $end
$var wire 1 " clock $end
$var wire 8 & entradaA8Bits [7:0] $end
$var wire 8 ' entradaB8Bits [7:0] $end
$var wire 4 ( opCode [3:0] $end
$var wire 9 ) resultado_subtracao [8:0] $end
$var wire 9 * resultado_soma [8:0] $end
$var wire 9 + resultado_comparacao [8:0] $end
$var reg 9 , saida9Bits [8:0] $end
$scope module comparador8bits_inst $end
$var wire 4 - codigoComparacao [3:0] $end
$var wire 8 . entradaA [7:0] $end
$var wire 8 / entradaB [7:0] $end
$var reg 9 0 saida9Bits [8:0] $end
$var integer 32 1 i [31:0] $end
$upscope $end
$scope module somador_inst $end
$var wire 8 2 A [7:0] $end
$var wire 8 3 B [7:0] $end
$var wire 9 4 S [8:0] $end
$var wire 7 5 C [6:0] $end
$scope module unidade1 $end
$var wire 1 6 A $end
$var wire 1 7 B $end
$var wire 1 8 C $end
$var wire 1 9 S $end
$upscope $end
$scope module unidade2 $end
$var wire 1 : A $end
$var wire 1 ; B $end
$var wire 1 < CIN $end
$var wire 1 = COUT $end
$var wire 1 > S $end
$upscope $end
$scope module unidade3 $end
$var wire 1 ? A $end
$var wire 1 @ B $end
$var wire 1 A CIN $end
$var wire 1 B COUT $end
$var wire 1 C S $end
$upscope $end
$scope module unidade4 $end
$var wire 1 D A $end
$var wire 1 E B $end
$var wire 1 F CIN $end
$var wire 1 G COUT $end
$var wire 1 H S $end
$upscope $end
$scope module unidade5 $end
$var wire 1 I A $end
$var wire 1 J B $end
$var wire 1 K CIN $end
$var wire 1 L COUT $end
$var wire 1 M S $end
$upscope $end
$scope module unidade6 $end
$var wire 1 N A $end
$var wire 1 O B $end
$var wire 1 P CIN $end
$var wire 1 Q COUT $end
$var wire 1 R S $end
$upscope $end
$scope module unidade7 $end
$var wire 1 S A $end
$var wire 1 T B $end
$var wire 1 U CIN $end
$var wire 1 V COUT $end
$var wire 1 W S $end
$upscope $end
$scope module unidade8 $end
$var wire 1 X A $end
$var wire 1 Y B $end
$var wire 1 Z CIN $end
$var wire 1 [ COUT $end
$var wire 1 \ S $end
$upscope $end
$upscope $end
$scope module subtrator_inst $end
$var wire 8 ] A [7:0] $end
$var wire 8 ^ B [7:0] $end
$var wire 9 _ S [8:0] $end
$var wire 7 ` C [6:0] $end
$scope module unidade1 $end
$var wire 1 a A $end
$var wire 1 b B $end
$var wire 1 c C $end
$var wire 1 d S $end
$upscope $end
$scope module unidade2 $end
$var wire 1 e A $end
$var wire 1 f B $end
$var wire 1 g CIN $end
$var wire 1 h COUT $end
$var wire 1 i S $end
$upscope $end
$scope module unidade3 $end
$var wire 1 j A $end
$var wire 1 k B $end
$var wire 1 l CIN $end
$var wire 1 m COUT $end
$var wire 1 n S $end
$upscope $end
$scope module unidade4 $end
$var wire 1 o A $end
$var wire 1 p B $end
$var wire 1 q CIN $end
$var wire 1 r COUT $end
$var wire 1 s S $end
$upscope $end
$scope module unidade5 $end
$var wire 1 t A $end
$var wire 1 u B $end
$var wire 1 v CIN $end
$var wire 1 w COUT $end
$var wire 1 x S $end
$upscope $end
$scope module unidade6 $end
$var wire 1 y A $end
$var wire 1 z B $end
$var wire 1 { CIN $end
$var wire 1 | COUT $end
$var wire 1 } S $end
$upscope $end
$scope module unidade7 $end
$var wire 1 ~ A $end
$var wire 1 !" B $end
$var wire 1 "" CIN $end
$var wire 1 #" COUT $end
$var wire 1 $" S $end
$upscope $end
$scope module unidade8 $end
$var wire 1 %" A $end
$var wire 1 &" B $end
$var wire 1 '" CIN $end
$var wire 1 (" COUT $end
$var wire 1 )" S $end
$upscope $end
$upscope $end
$upscope $end
$upscope $end
$enddefinitions $end
$comment Show the parameter values. $end
$dumpall
$end
#0
$dumpvars
x)"
x("
x'"
x&"
x%"
x$"
x#"
x""
x!"
x~
x}
x|
x{
xz
xy
xx
xw
xv
xu
xt
xs
xr
xq
xp
xo
xn
xm
xl
xk
xj
xi
xh
xg
xf
xe
xd
xc
xb
xa
bx `
bx _
bx ^
bx ]
x\
x[
xZ
xY
xX
xW
xV
xU
xT
xS
xR
xQ
xP
xO
xN
xM
xL
xK
xJ
xI
xH
xG
xF
xE
xD
xC
xB
xA
x@
x?
x>
x=
x<
x;
x:
x9
x8
x7
x6
bx 5
bx 4
bx 3
bx 2
b1000 1
b0 0
bx /
bx .
b0 -
bx ,
b0 +
bx *
bx )
b0 (
bx '
bx &
b0 %
bx $
bx #
0"
bx !
$end
#5
1"
#10
0R
0P
1("
0L
1)"
1M
1'"
0K
1#"
0G
1$"
1H
1""
0F
1n
1|
0B
0l
0h
0s
1x
1}
1C
0W
0\
1q
0v
1{
0A
0U
0Z
0i
1m
0r
1w
0>
0=
0Q
0V
0[
0g
0<
b1110100 `
0c
b11101 *
b11101 4
19
b0 5
08
b111110101 )
b111110101 _
1d
07
0;
1@
0E
1J
0O
0T
0Y
0b
0f
1k
0p
1u
0z
0!"
0&"
b1000 1
16
0:
0?
1D
0I
0N
0S
0X
1a
0e
0j
1o
0t
0y
0~
0%"
0"
b10100 $
b10100 '
b10100 /
b10100 3
b10100 ^
b1001 #
b1001 &
b1001 .
b1001 2
b1001 ]
#15
b11101 !
b11101 ,
1"
#20
0("
0)"
0'"
0#"
0$"
0""
0|
0}
0q
0{
1R
1W
1\
0m
0w
1>
1K
0v
1A
1F
1P
1U
1Z
1<
1H
1G
0s
b0 `
0r
1=
1C
1B
1M
1L
1Q
1V
1[
0n
0x
b111111110 *
b111111110 4
09
b1111111 5
18
b0 )
b0 _
0d
17
1;
1E
1O
1T
1Y
1b
1f
1p
1z
1!"
1&"
b1000 1
1:
1?
1I
1N
1S
1X
1e
1j
1t
1y
1~
1%"
0"
b11111111 $
b11111111 '
b11111111 /
b11111111 3
b11111111 ^
b11111111 #
b11111111 &
b11111111 .
b11111111 2
b11111111 ]
#25
b111111110 !
b111111110 ,
1"
#30
b1000 1
0"
b1 %
b1 (
b1 -
#35
b0 !
b0 ,
1"
#40
0R
0P
0L
0K
0G
0F
0B
0W
0\
1q
0A
0U
0Z
b100 `
1m
0=
0Q
b1 5
0V
0[
1H
1M
0s
1x
b11110 *
b11110 4
1C
b10100 )
b10100 _
1n
0;
0E
0J
0O
0T
0Y
0f
0p
0u
0z
0!"
0&"
b1000 1
0:
0?
0N
0S
0X
0e
0j
0y
0~
0%"
0"
b101 $
b101 '
b101 /
b101 3
b101 ^
b11001 #
b11001 &
b11001 .
b11001 2
b11001 ]
#45
b10100 !
b10100 ,
1"
#50
0("
0)"
0'"
0#"
0$"
0""
0|
0}
0{
0w
0q
1R
1W
1\
0m
1K
1P
0v
1A
1F
1U
1Z
1H
1G
1M
1L
0s
b0 `
0r
0x
1=
1C
1B
1Q
b1111111 5
1V
b111111110 *
b111111110 4
1[
b0 )
b0 _
0n
1;
1E
1J
1O
1T
1Y
1f
1p
1u
1z
1!"
1&"
b1000 1
1:
1?
1N
1S
1X
1e
1j
1y
1~
1%"
0"
b11111111 $
b11111111 '
b11111111 /
b11111111 3
b11111111 ^
b11111111 #
b11111111 &
b11111111 .
b11111111 2
b11111111 ]
#55
b0 !
b0 ,
1"
#60
0H
0F
0B
0R
1v
0P
1r
0L
0A
1s
0=
0W
1l
1q
0K
0U
1h
b1110 `
1m
0G
0Q
0[
1M
0x
0<
1>
b10010110 *
b10010110 4
1C
1i
b1010 )
b1010 _
0n
b1000000 5
08
07
0E
0J
0O
0Y
0b
0p
0u
0z
0&"
06
0:
0?
0D
0N
0X
0a
0e
0j
0o
0y
0%"
b1000 1
0"
b1000110 $
b1000110 '
b1000110 /
b1000110 3
b1000110 ^
b1010000 #
b1010000 &
b1010000 .
b1010000 2
b1010000 ]
b10 %
b10 (
b10 -
#65
b1 !
b1 ,
1"
#70
1("
1)"
1'"
1#"
1$"
1""
1n
1|
0l
0q
1}
1W
0h
0m
1{
1U
0>
b11011100 *
b11011100 4
1H
0i
b111101100 )
b111101100 _
1s
b1111000 `
1w
b1100000 5
1Q
0;
0@
1E
1J
1O
0f
0k
1p
1u
1z
b1000 1
1?
0I
1N
1j
0t
1y
0"
b1111000 $
b1111000 '
b1111000 /
b1111000 3
b1111000 ^
b1100100 #
b1100100 &
b1100100 .
b1100100 2
b1100100 ]
#75
b0 !
b0 ,
1"
#80
0\
1K
0Z
1G
0V
0H
1R
1F
1""
1P
0U
0C
1B
0n
b1111000 `
1|
1>
1M
1L
b11100 5
0Q
1W
b101110010 *
b101110010 4
1[
1i
1x
b110111010 )
b110111010 _
0$"
1@
0O
1Y
1k
0z
1&"
1:
1I
0N
0S
1X
1e
1t
0y
0~
1%"
b1000 1
0"
b11011100 $
b11011100 '
b11011100 /
b11011100 3
b11011100 ^
b10010110 #
b10010110 &
b10010110 .
b10010110 2
b10010110 ]
b11 %
b11 (
b11 -
#85
b1 !
b1 ,
1"
#90
1q
1$"
1Z
1m
0""
1V
1n
0|
1v
1l
0}
0W
1r
1h
0{
1U
0M
0\
1[
0x
b1001110 `
0w
0)"
0("
1H
b1111100 5
1Q
1s
b100101011 *
b100101011 4
19
b1001111 )
b1001111 _
1d
1;
0J
1O
0Y
1f
0u
1z
0&"
b1000 1
16
0:
1D
1N
1a
0e
1o
1y
0"
b1101110 $
b1101110 '
b1101110 /
b1101110 3
b1101110 ^
b10111101 #
b10111101 &
b10111101 .
b10111101 2
b10111101 ]
#95
b0 !
b0 ,
1"
#100
0""
0|
0n
0}
0R
0l
0{
0Z
0s
0'"
1C
0H
0K
0P
0U
0h
0w
0("
0V
0q
0v
0#"
1A
0F
0G
0L
0Q
0[
0W
0m
b0 `
0r
0$"
0>
1=
b10 5
0B
0M
0\
0i
0x
0)"
b100 *
b100 4
09
b0 )
b0 _
0d
0@
0E
0O
0T
0k
0p
0z
0!"
06
1:
0?
0D
0I
0N
0X
0a
1e
0j
0o
0t
0y
0%"
b1000 1
0"
b10 $
b10 '
b10 /
b10 3
b10 ^
b10 #
b10 &
b10 .
b10 2
b10 ]
b100 %
b100 (
b100 -
#105
b1 !
b1 ,
1"
#110
1W
1U
1v
1Q
1r
1s
1q
1P
1m
1L
1n
1l
1{
0C
1H
1h
b11110 `
1w
0A
1F
1K
0M
0x
1>
0=
1B
b111100 5
1G
0R
1i
0}
b1001011 *
b1001011 4
19
b1111 )
b1111 _
1d
1@
1E
1J
1k
1p
1u
b1000 1
16
0:
1?
1D
1N
1a
0e
1j
1o
1y
0"
b11110 $
b11110 '
b11110 /
b11110 3
b11110 ^
b101101 #
b101101 &
b101101 .
b101101 2
b101101 ]
#115
1"
#120
1K
0[
0{
1G
0w
0l
0""
0U
0Z
0h
0|
0v
1("
1A
1F
0Q
0V
0H
1\
0s
b100 `
0r
1)"
0>
1=
0C
b11110 5
1B
1M
1R
1W
0i
1n
0x
0}
1$"
b11110000 *
b11110000 4
09
b111000100 )
b111000100 _
0d
0E
1Y
0p
1&"
b1000 1
06
1:
0?
1I
0N
1S
0a
1e
0j
1t
0y
1~
0"
b10010110 $
b10010110 '
b10010110 /
b10010110 3
b10010110 ^
b1011010 #
b1011010 &
b1011010 .
b1011010 2
b1011010 ]
#125
b0 !
b0 ,
1"
#130
0'"
0#"
0""
0|
0}
0{
0w
0q
0x
0m
0v
0("
1H
0\
0s
b0 `
0r
0)"
1C
b111100 *
b111100 4
0W
0n
b0 )
b0 _
0$"
1E
0Y
1p
0&"
1?
0S
1j
0~
b1000 1
0"
b11110 $
b11110 '
b11110 /
b11110 3
b11110 ^
b11110 #
b11110 &
b11110 .
b11110 2
b11110 ]
b101 %
b101 (
b101 -
#135
b1 !
b1 ,
1"
#140
0H
1\
1("
0F
1Z
0B
1V
1)"
1'"
b1000000 `
1#"
0A
1U
1C
b10110100 *
b10110100 4
0W
1n
b111000100 )
b111000100 _
1$"
0=
b1111000 5
1Q
0;
0@
1O
1T
0f
0k
1z
1!"
b1000 1
0:
1N
0e
1y
0"
b1111000 $
b1111000 '
b1111000 /
b1111000 3
b1111000 ^
b111100 #
b111100 &
b111100 .
b111100 2
b111100 ]
#145
1"
#150
0U
0Q
1""
1'"
0M
1q
0P
1|
1#"
0("
0K
b1100100 `
1m
0L
1[
1H
b1000000 5
0G
0s
1R
0W
b100101100 *
b100101100 4
0\
1}
1$"
b1100100 )
b1100100 _
0)"
1@
0E
0J
1k
0p
0u
b1000 1
0?
0I
0N
1S
1X
0j
0t
0y
1~
1%"
0"
b1100100 $
b1100100 '
b1100100 /
b1100100 3
b1100100 ^
b11001000 #
b11001000 &
b11001000 .
b11001000 2
b11001000 ]
#155
b0 !
b0 ,
1"
#160
0{
0w
0x
0$"
0v
0""
0q
1W
0r
0|
0("
0m
0'"
1A
1P
1U
0Z
0[
1C
0n
b0 `
0#"
1=
0H
1L
1R
1Q
b110010 5
0V
b1100100 *
b1100100 4
0\
0s
0}
b0 )
b0 _
0)"
1;
0@
1J
0T
1f
0k
1u
0!"
1:
0D
1I
1N
0S
0X
1e
0o
1t
1y
0~
0%"
b1000 1
0"
b110010 $
b110010 '
b110010 /
b110010 3
b110010 ^
b110010 #
b110010 &
b110010 .
b110010 2
b110010 ]
b110 %
b110 (
b110 -
#165
b1 !
b1 ,
1"
#170
0K
0G
0U
0Q
0\
1{
1v
0F
0Z
1w
b11000 `
1r
0A
0B
0P
0V
1H
1R
1s
0}
0=
1C
1M
b0 5
0L
b1111100 *
b1111100 4
1W
1n
0x
b1001100 )
b1001100 _
1$"
0;
1E
0O
0f
1p
0z
b1000 1
0:
1?
0I
1S
0e
1j
0t
1~
0"
b11000 $
b11000 '
b11000 /
b11000 3
b11000 ^
b1100100 #
b1100100 &
b1100100 .
b1100100 2
b1100100 ]
#175
b0 !
b0 ,
1"
#180
0("
0)"
0'"
0#"
1K
0{
1G
0w
0""
0H
0v
0|
1F
0r
1P
0C
1B
1g
0n
1>
1M
b11100 5
1L
1R
0W
0i
0x
0}
0$"
b110011 *
b110011 4
19
b1001 )
b1001 _
1d
b1 `
1c
17
1@
0E
1b
1k
0p
b1000 1
1:
1D
1I
0N
0S
1e
1o
1t
0y
0~
0"
b10101 $
b10101 '
b10101 /
b10101 3
b10101 ^
b11110 #
b11110 &
b11110 .
b11110 2
b11110 ]
#185
1"
#190
0("
0)"
0'"
0#"
0$"
0""
0|
0}
0{
0w
0x
0v
0r
0q
0m
1C
0n
1W
1\
1A
0l
1U
1Z
0g
1=
1H
0i
0h
0s
1<
1Q
1V
1[
b0 `
0c
b111111110 *
b111111110 4
09
b1111111 5
18
b0 )
b0 _
0d
1;
1E
1O
1T
1Y
1f
1p
1z
1!"
1&"
16
1N
1S
1X
1a
1y
1~
1%"
b1000 1
0"
b11111111 $
b11111111 '
b11111111 /
b11111111 3
b11111111 ^
b11111111 #
b11111111 &
b11111111 .
b11111111 2
b11111111 ]
b111 %
b111 (
b111 -
#195
1"
#200
0C
0H
0M
0R
0W
0\
0A
0F
0K
0P
0U
0Z
0>
0=
0B
0G
0L
0Q
0V
b0 *
b0 4
0[
0<
b0 5
08
07
0;
0@
0E
0J
0O
0T
0Y
0b
0f
0k
0p
0u
0z
0!"
0&"
b11111111 +
b11111111 0
b1000 1
06
0:
0?
0D
0I
0N
0S
0X
0a
0e
0j
0o
0t
0y
0~
0%"
0"
b0 $
b0 '
b0 /
b0 3
b0 ^
b0 #
b0 &
b0 .
b0 2
b0 ]
