PCG/ula8its/ula.v

module ula (entradaA8Bits, entradaB8Bits, opCode, clock, saida9Bits);
    input [7:0] entradaA8Bits, entradaB8Bits;
    input [3:0] opCode;
    input clock;

    integer i;

    output reg [8:0] saida9Bits;

    always @(posedge clock) begin
        case (opCode)
            4'b0: // SOMA
                saida9Bits = entradaA8Bits + entradaB8Bits;
            4'b1: // SUBTRAÇÃO
                saida9Bits = entradaA8Bits - entradaB8Bits;
            4'b10: // MAIOR QUE >
                saida9Bits = entradaA8Bits > entradaB8Bits;
            4'b11: // MENOR QUE <
                saida9Bits = entradaA8Bits < entradaB8Bits;
            4'b100: // MAIOR OU IGUAL >= 
                saida9Bits = entradaA8Bits >= entradaB8Bits;
            4'b101: // MENOR OU IGUAL <=
                saida9Bits = entradaA8Bits <= entradaB8Bits;
            4'b110: // IGUAL
                saida9Bits = entradaA8Bits == entradaB8Bits;
            4'b111: // NOT ! 
                begin
                    for (i = 0; i < 8; i = i + 1) begin
                        if (entradaA8Bits[i] == entradaA8Bits[i])
                            if (entradaA8Bits[i]) 
                                saida9Bits[i] = 0;
                            else
                                saida9Bits[i] = 1;
                        else
                            saida9Bits[i] = ~entradaA8Bits[i];
                    end
                    saida9Bits[8] = 0;
                end
            4'b1000: // AND
                begin
                    for (i = 0; i < 8; i = i + 1) begin
                        saida9Bits[i] = entradaA8Bits[i] & entradaB8Bits[i];
                    end
                    saida9Bits[8] = 0;
                end
            4'b1001: // OR
                begin
                    for (i = 0; i < 8; i = i + 1) begin
                        saida9Bits[i] = entradaA8Bits[i] | entradaB8Bits[i];
                    end
                    saida9Bits[8] = 0;
                end
            4'b1010: // XOR
                begin
                    for (i = 0; i < 8; i = i + 1) begin
                        saida9Bits[i] = entradaA8Bits[i] ^ entradaB8Bits[i];
                    end
                    saida9Bits[8] = 0;
                end
            4'b1011: // XNOR
                begin
                    for (i = 0; i < 8; i = i + 1) begin
                        saida9Bits[i] = entradaA8Bits[i] ~^ entradaB8Bits[i];
                    end
                    saida9Bits[8] = 0;
                end

            default:  saida9Bits = 9'bx;
        endcase
    end

endmodule

PCG/ula8its/ula_tb.v
`timescale 1ns/1ns
`include "ula.v"

module ula_tb;

    reg [7:0] entradaA8Bits, entradaB8Bits;
    reg [3:0] opCode;
    reg clock;

    wire [8:0] saida9Bits;
    
    ula uut(entradaA8Bits, entradaB8Bits, opCode, clock, saida9Bits);

    initial begin
        $dumpfile("ula_tb.vcd");
        $dumpvars(0, ula_tb);

        // TESTE SOMA, 9 + 20 = 29
        opCode = 4'b0; #10;
        entradaA8Bits = 8'b1001;
        entradaB8Bits = 8'b10100; #10;

        // TESTE SOMA, 255 + 255 = 510
        entradaA8Bits = 8'b11111111;
        entradaB8Bits = 8'b11111111; #10;

        // ~~~~~~~~~~~~~~~~~~~~~~~~~~~~~~~~~~~~~~~~~~~~~~~~~~~~~~~~~~~~~~~~~~~~~~~~~~~~~~~~~~~~~~~~~~~~~~~~~~~~~ //

        // TESTE SUBTRACAO, 25 - 5 = 20
        opCode = 4'b1; #10;
        entradaA8Bits = 8'b11001;
        entradaB8Bits = 8'b101; #10;

        // TESTE SUBTRACAO, 255 - 255 = 0
        entradaA8Bits = 8'b11111111;
        entradaB8Bits = 8'b11111111; #10;

        // ~~~~~~~~~~~~~~~~~~~~~~~~~~~~~~~~~~~~~~~~~~~~~~~~~~~~~~~~~~~~~~~~~~~~~~~~~~~~~~~~~~~~~~~~~~~~~~~~~~~~~ //

        // TESTE MAIOR QUE, 80 > 70 = TRUE
        opCode = 4'b10;
        entradaA8Bits = 8'b1010000;
        entradaB8Bits = 8'b1000110; #10;

        // TESTE MAIOR QUE, 100 > 120 = FALSE
        entradaA8Bits = 8'b1100100;
        entradaB8Bits = 8'b1111000; #10;

        // ~~~~~~~~~~~~~~~~~~~~~~~~~~~~~~~~~~~~~~~~~~~~~~~~~~~~~~~~~~~~~~~~~~~~~~~~~~~~~~~~~~~~~~~~~~~~~~~~~~~~~ //

        // TESTE MENOR QUE, 150 < 220 = TRUE
        opCode = 4'b11;
        entradaA8Bits = 8'b10010110;
        entradaB8Bits = 8'b11011100; #10;

        // TESTE MENOR QUE, 189 < 110 = FALSE
        entradaA8Bits = 8'b10111101;
        entradaB8Bits = 8'b1101110; #10;

        // ~~~~~~~~~~~~~~~~~~~~~~~~~~~~~~~~~~~~~~~~~~~~~~~~~~~~~~~~~~~~~~~~~~~~~~~~~~~~~~~~~~~~~~~~~~~~~~~~~~~~~ //

        // TESTE MAIOR OU IGUAL, 2 >= 2 = TRUE
        opCode = 4'b100;
        entradaA8Bits = 8'b10;
        entradaB8Bits = 8'b10; #10;

        // TESTE MAIOR OU IGUAL, 45 >= 30 = TRUE
        opCode = 4'b100;
        entradaA8Bits = 8'b101101;
        entradaB8Bits = 8'b11110; #10;

        // TESTE MAIOR OU IGUAL, 90 >= 150 = FALSE
        opCode = 4'b100;
        entradaA8Bits = 8'b1011010;
        entradaB8Bits = 8'b10010110; #10;

        // ~~~~~~~~~~~~~~~~~~~~~~~~~~~~~~~~~~~~~~~~~~~~~~~~~~~~~~~~~~~~~~~~~~~~~~~~~~~~~~~~~~~~~~~~~~~~~~~~~~~~~ //

        // TESTE MENOR OU IGUAL, 30 <= 30 = TRUE
        opCode = 4'b101;
        entradaA8Bits = 8'b11110;
        entradaB8Bits = 8'b11110; #10;

        // TESTE MENOR OU IGUAL, 60 <= 120 = TRUE (primeiro número menor que o segundo)
        entradaA8Bits = 8'b111100;
        entradaB8Bits = 8'b1111000; #10;

        // TESTE MENOR OU IGUAL, 200 <= 100 = FALSE (primeiro número maior que o segundo)
        entradaA8Bits = 8'b11001000;
        entradaB8Bits = 8'b1100100; #10;

        // ~~~~~~~~~~~~~~~~~~~~~~~~~~~~~~~~~~~~~~~~~~~~~~~~~~~~~~~~~~~~~~~~~~~~~~~~~~~~~~~~~~~~~~~~~~~~~~~~~~~~~ //

        // TESTE IGUAL, 50 == 50 = TRUE
        opCode = 4'b110;
        entradaA8Bits = 8'b110010;
        entradaB8Bits = 8'b110010; #10;

        // TESTE IGUAL, 100 == 24 = FALSE
        entradaA8Bits = 8'b1100100;
        entradaB8Bits = 8'b11000;  #10;

        // TESTE IGUAL, 30 == 21 = FALSE
        entradaA8Bits = 8'b11110;
        entradaB8Bits = 8'b10101; #10;

        // ~~~~~~~~~~~~~~~~~~~~~~~~~~~~~~~~~~~~~~~~~~~~~~~~~~~~~~~~~~~~~~~~~~~~~~~~~~~~~~~~~~~~~~~~~~~~~~~~~~~~~ //

        // TESTE NOT, 1111 1111 COM 1111 1111 = 0000 0000
        opCode = 4'b111;
        entradaA8Bits = 8'b11111111;
        entradaB8Bits = 8'b11111111; #10;

        // TESTE NOT, 0000 0000 COM 0000 0000 = 1111 1111
        entradaA8Bits = 8'b0;
        entradaB8Bits = 8'b0; #10;

        // TESTE NOT, 0101 0101 COM 0101 0101 = 10101010
        entradaA8Bits = 8'b01010101;
        entradaB8Bits = 8'b01010101; #10;

        // TESTE NOT, 1010 1010 COM 1010 1010 = 01010101
        entradaA8Bits = 8'b10101010;
        entradaB8Bits = 8'b10101010; #10;

        // TESTE NOT, 1100 0011 COM 1100 0011 = 00111100
        entradaA8Bits = 8'b11000011;
        entradaB8Bits = 8'b11000011; #10;

        // TESTE NOT, 0011 1100 COM 0011 1100 = 11000011
        entradaA8Bits = 8'b111100;
        entradaB8Bits = 8'b111100; #10;

        // ~~~~~~~~~~~~~~~~~~~~~~~~~~~~~~~~~~~~~~~~~~~~~~~~~~~~~~~~~~~~~~~~~~~~~~~~~~~~~~~~~~~~~~~~~~~~~~~~~~~~~ //

        // TESTE AND, 1111 1111 COM 1111 1111 = 11111111
        opCode = 4'b1000;
        entradaA8Bits = 8'b11111111;
        entradaB8Bits = 8'b11111111; #10;        

        // TESTE AND, 0000 0000 COM 0000 0000 = 00000000
        entradaA8Bits = 8'b0;
        entradaB8Bits = 8'b0; #10;

        // TESTE AND, 1010 1010 COM 1010 1010 = 10101010
        entradaA8Bits = 8'b10101010;
        entradaB8Bits = 8'b10101010; #10;

        // TESTE AND, 1010 1010 COM 0101 0101 = 00000000
        entradaA8Bits = 8'b10101010;
        entradaB8Bits = 8'b01010101; #10;

        // ~~~~~~~~~~~~~~~~~~~~~~~~~~~~~~~~~~~~~~~~~~~~~~~~~~~~~~~~~~~~~~~~~~~~~~~~~~~~~~~~~~~~~~~~~~~~~~~~~~~~~ //

        // TESTE OR, 1111 1111 COM 1111 1111 = 11111111
        opCode = 4'b1001;
        entradaA8Bits = 8'b11111111;
        entradaB8Bits = 8'b11111111; #10;

        // TESTE OR, 1010 1010 COM 0101 0101 = 11111111
        entradaA8Bits = 8'b10101010;
        entradaB8Bits = 8'b01010101; #10;

        // TESTE OR, 0000 0000 COM 0000 0000 = 00000000
        entradaA8Bits = 8'b0;
        entradaB8Bits = 8'b0; #10;

        // TESTE OR, 1010 1010 COM 1010 1010 = 10101010
        entradaA8Bits = 8'b10101010;
        entradaB8Bits = 8'b10101010; #10;

        // ~~~~~~~~~~~~~~~~~~~~~~~~~~~~~~~~~~~~~~~~~~~~~~~~~~~~~~~~~~~~~~~~~~~~~~~~~~~~~~~~~~~~~~~~~~~~~~~~~~~~~ //

        // TESTE XOR, 1111 1111 COM 1111 1111 = 00000000
        opCode = 4'b1010;
        entradaA8Bits = 8'b11111111;
        entradaB8Bits = 8'b11111111; #10;

        // TESTE XOR, 0000 0000 COM 0000 0000 = 00000000
        entradaA8Bits = 8'b0;
        entradaB8Bits = 8'b0; #10;

        // TESTE XOR, 1010 1010 COM 0101 0101 = 11111111
        entradaA8Bits = 8'b10101010;
        entradaB8Bits = 8'b01010101; #10;

        // TESTE XOR, 1010 1010 COM 1010 1010 = 00000000
        entradaA8Bits = 8'b10101010;
        entradaB8Bits = 8'b10101010; #10;

        // ~~~~~~~~~~~~~~~~~~~~~~~~~~~~~~~~~~~~~~~~~~~~~~~~~~~~~~~~~~~~~~~~~~~~~~~~~~~~~~~~~~~~~~~~~~~~~~~~~~~~~ //

        // TESTE XNOR, 1111 1111 COM 1111 1111 = 11111111
        opCode = 4'b1011;
        entradaA8Bits = 8'b11111111;
        entradaB8Bits = 8'b11111111; #10;

        // TESTE XNOR, 0000 0000 COM 0000 0000 = 11111111
        entradaA8Bits = 8'b0;
        entradaB8Bits = 8'b0; #10;

        // TESTE XNOR, 1010 1010 COM 0101 0101 = 00000000
        entradaA8Bits = 8'b10101010;
        entradaB8Bits = 8'b01010101; #10;

        // TESTE XNOR, 1010 1010 COM 1010 1010 = 11111111
        entradaA8Bits = 8'b10101010;
        entradaB8Bits = 8'b10101010; #10;

        $display("Teste completo");
        $finish;
    end

    initial begin
        clock = 0;
        forever #5 clock = ~clock ;
    end

endmodule

PCG/ula8its/ula_tb.vcd
$date
	Mon Nov 18 02:01:45 2024
$end
$version
	Icarus Verilog
$end
$timescale
	1ns
$end
$scope module ula_tb $end
$var wire 9 ! saida9Bits [8:0] $end
$var reg 1 " clock $end
$var reg 8 # entradaA8Bits [7:0] $end
$var reg 8 $ entradaB8Bits [7:0] $end
$var reg 4 % opCode [3:0] $end
$scope module uut $end
$var wire 1 " clock $end
$var wire 8 & entradaA8Bits [7:0] $end
$var wire 8 ' entradaB8Bits [7:0] $end
$var wire 4 ( opCode [3:0] $end
$var reg 9 ) saida9Bits [8:0] $end
$var integer 32 * i [31:0] $end
$upscope $end
$upscope $end
$enddefinitions $end
$comment Show the parameter values. $end
$dumpall
$end
#0
$dumpvars
bx *
bx )
b0 (
bx '
bx &
b0 %
bx $
bx #
0"
bx !
$end
#5
1"
#10
0"
b10100 $
b10100 '
b1001 #
b1001 &
#15
b11101 !
b11101 )
1"
#20
0"
b11111111 $
b11111111 '
b11111111 #
b11111111 &
#25
b111111110 !
b111111110 )
1"
#30
0"
b1 %
b1 (
#35
b0 !
b0 )
1"
#40
0"
b101 $
b101 '
b11001 #
b11001 &
#45
b10100 !
b10100 )
1"
#50
0"
b11111111 $
b11111111 '
b11111111 #
b11111111 &
#55
b0 !
b0 )
1"
#60
0"
b1000110 $
b1000110 '
b1010000 #
b1010000 &
b10 %
b10 (
#65
b1 !
b1 )
1"
#70
0"
b1111000 $
b1111000 '
b1100100 #
b1100100 &
#75
b0 !
b0 )
1"
#80
0"
b11011100 $
b11011100 '
b10010110 #
b10010110 &
b11 %
b11 (
#85
b1 !
b1 )
1"
#90
0"
b1101110 $
b1101110 '
b10111101 #
b10111101 &
#95
b0 !
b0 )
1"
#100
0"
b10 $
b10 '
b10 #
b10 &
b100 %
b100 (
#105
b1 !
b1 )
1"
#110
0"
b11110 $
b11110 '
b101101 #
b101101 &
#115
1"
#120
0"
b10010110 $
b10010110 '
b1011010 #
b1011010 &
#125
b0 !
b0 )
1"
#130
0"
b11110 $
b11110 '
b11110 #
b11110 &
b101 %
b101 (
#135
b1 !
b1 )
1"
#140
0"
b1111000 $
b1111000 '
b111100 #
b111100 &
#145
1"
#150
0"
b1100100 $
b1100100 '
b11001000 #
b11001000 &
#155
b0 !
b0 )
1"
#160
0"
b110010 $
b110010 '
b110010 #
b110010 &
b110 %
b110 (
#165
b1 !
b1 )
1"
#170
0"
b11000 $
b11000 '
b1100100 #
b1100100 &
#175
b0 !
b0 )
1"
#180
0"
b10101 $
b10101 '
b11110 #
b11110 &
#185
1"
#190
0"
b11111111 $
b11111111 '
b11111111 #
b11111111 &
b111 %
b111 (
#195
b1000 *
1"
#200
0"
b0 $
b0 '
b0 #
b0 &
#205
b11111111 !
b11111111 )
b1000 *
1"
#210
0"
b1010101 $
b1010101 '
b1010101 #
b1010101 &
#215
b10101010 !
b10101010 )
b1000 *
1"
#220
0"
b10101010 $
b10101010 '
b10101010 #
b10101010 &
#225
b1010101 !
b1010101 )
b1000 *
1"
#230
0"
b11000011 $
b11000011 '
b11000011 #
b11000011 &
#235
b111100 !
b111100 )
b1000 *
1"
#240
0"
b111100 $
b111100 '
b111100 #
b111100 &
#245
b11000011 !
b11000011 )
b1000 *
1"
#250
0"
b11111111 $
b11111111 '
b11111111 #
b11111111 &
b1000 %
b1000 (
#255
b11111111 !
b11111111 )
b1000 *
1"
#260
0"
b0 $
b0 '
b0 #
b0 &
#265
b0 !
b0 )
b1000 *
1"
#270
0"
b10101010 $
b10101010 '
b10101010 #
b10101010 &
#275
b10101010 !
b10101010 )
b1000 *
1"
#280
0"
b1010101 $
b1010101 '
#285
b0 !
b0 )
b1000 *
1"
#290
0"
b11111111 $
b11111111 '
b11111111 #
b11111111 &
b1001 %
b1001 (
#295
b11111111 !
b11111111 )
b1000 *
1"
#300
0"
b1010101 $
b1010101 '
b10101010 #
b10101010 &
#305
b1000 *
1"
#310
0"
b0 $
b0 '
b0 #
b0 &
#315
b0 !
b0 )
b1000 *
1"
#320
0"
b10101010 $
b10101010 '
b10101010 #
b10101010 &
#325
b10101010 !
b10101010 )
b1000 *
1"
#330
0"
b11111111 $
b11111111 '
b11111111 #
b11111111 &
b1010 %
b1010 (
#335
b0 !
b0 )
b1000 *
1"
#340
0"
b0 $
b0 '
b0 #
b0 &
#345
b1000 *
1"
#350
0"
b1010101 $
b1010101 '
b10101010 #
b10101010 &
#355
b11111111 !
b11111111 )
b1000 *
1"
#360
0"
b10101010 $
b10101010 '
#365
b0 !
b0 )
b1000 *
1"
#370
0"
b11111111 $
b11111111 '
b11111111 #
b11111111 &
b1011 %
b1011 (
#375
b11111111 !
b11111111 )
b1000 *
1"
#380
0"
b0 $
b0 '
b0 #
b0 &
#385
b1000 *
1"
#390
0"
b1010101 $
b1010101 '
b10101010 #
b10101010 &
#395
b0 !
b0 )
b1000 *
1"
#400
0"
b10101010 $
b10101010 '
#405
b11111111 !
b11111111 )
b1000 *
1"
