ATIVIDADES-PRATICAS/ATIVIDADE-PRATICA-4/somador e subtrator de n bits/subtrator/subtrator_completo.v
module subtrator_completo (A, B, CIN, S, COUT);

    input A, B, CIN;
    output S, COUT;

    assign S = A ^ B ^ CIN; 
    assign COUT = ~A & B | ~A & CIN | B & CIN;

endmodule

ATIVIDADES-PRATICAS/ATIVIDADE-PRATICA-4/subtrator/completo/subtrator_completo_tb.v
`timescale 1ns/1ns
`include "subtrator_completo.v"

module subtrator_completo_tb;

    reg A, B, CIN;
    wire S, COUT;

    subtrator_completo uut(A, B, CIN, S, COUT);

    initial begin
        $dumpfile("subtrator_completo.vcd");
        $dumpvars(0, subtrator_completo_tb);

        A = 0;
        B = 0;
        CIN = 0;#20;

        A = 0;
        B = 0;
        CIN = 1;#20;

        A = 0;
        B = 1;
        CIN = 0;#20;

        A = 0;
        B = 1;
        CIN = 1;#20;
        
        A = 1;
        B = 0;
        CIN = 0;#20;

        A = 1;
        B = 0;
        CIN = 1;#20;

        A = 1;
        B = 1;
        CIN = 0;#20;

        A = 1;
        B = 1;
        CIN = 1;#20;

        $display("Teste completo");
    end

endmodule

ATIVIDADES-PRATICAS/ATIVIDADE-PRATICA-4/subtrator/completo/subtrator_completo.vcd
$date
	Fri Sep 27 10:31:39 2024
$end
$version
	Icarus Verilog
$end
$timescale
	1ns
$end
$scope module subtrator_completo_tb $end
$var wire 1 ! S $end
$var wire 1 " COUT $end
$var reg 1 # A $end
$var reg 1 $ B $end
$var reg 1 % CIN $end
$scope module uut $end
$var wire 1 # A $end
$var wire 1 $ B $end
$var wire 1 % CIN $end
$var wire 1 " COUT $end
$var wire 1 ! S $end
$upscope $end
$upscope $end
$enddefinitions $end
$comment Show the parameter values. $end
$dumpall
$end
#0
$dumpvars
0%
0$
0#
0"
0!
$end
#20
1"
1!
1%
#40
0%
1$
#60
0!
1%
#80
0"
1!
0%
0$
1#
#100
0!
1%
#120
0%
1$
#140
1"
1!
1%
