ATIVIDADES-PRATICAS/ATIVIDADE-PRATICA-3/decoder/decoder.v
module decoder (A, E, D);
    input [2:0] A;
    input E;
    output reg [7:0] D;

    always @(E or A) begin
        if (E == 1'b1) begin
            case (A)
                3'b000: D = 8'b00000001;
                3'b001: D = 8'b00000010;
                3'b010: D = 8'b00000100;
                3'b011: D = 8'b00001000;
                3'b100: D = 8'b00010000;
                3'b101: D = 8'b00100000;
                3'b110: D = 8'b01000000;
                3'b111: D = 8'b10000000;

                default:  D = 8'b00000000;
            endcase
        end
        else
            D = 8'b00000000;
    end

endmodule

ATIVIDADES-PRATICAS/ATIVIDADE-PRATICA-3/decoder/decoder_tb.v
`timescale 1ns/1ns
`include "decoder.v"

module decoder_tb;

    reg [2:0] A;
    reg E;

    wire [7:0] D;

    decoder uut(A, E, D);

    initial begin
        $dumpfile("decoder_tb.vcd");
        $dumpvars(0, decoder_tb);

        E = 1'b1;
        A = 3'b000; #10;
        A = 3'b001; #10;
        A = 3'b010; #10;
        A = 3'b011; #10;
        A = 3'b100; #10;
        A = 3'b101; #10;
        A = 3'b110; #10;
        A = 3'b111; #10;
        
        E = 1'b0; #10;

        $display("Teste completo");
    end

endmodule

ATIVIDADES-PRATICAS/ATIVIDADE-PRATICA-3/decoder/decoder_tb.vcd
$date
	Fri Sep 20 10:44:53 2024
$end
$version
	Icarus Verilog
$end
$timescale
	1ns
$end
$scope module decoder_tb $end
$var wire 8 ! D [7:0] $end
$var reg 3 " A [2:0] $end
$var reg 1 # E $end
$scope module uut $end
$var wire 3 $ A [2:0] $end
$var wire 1 # E $end
$var reg 8 % D [7:0] $end
$upscope $end
$upscope $end
$enddefinitions $end
$comment Show the parameter values. $end
$dumpall
$end
#0
$dumpvars
b1 %
b0 $
1#
b0 "
b1 !
$end
#10
b10 !
b10 %
b1 "
b1 $
#20
b100 !
b100 %
b10 "
b10 $
#30
b1000 !
b1000 %
b11 "
b11 $
#40
b10000 !
b10000 %
b100 "
b100 $
#50
b100000 !
b100000 %
b101 "
b101 $
#60
b1000000 !
b1000000 %
b110 "
b110 $
#70
b10000000 !
b10000000 %
b111 "
b111 $
#80
b0 !
b0 %
0#
