exercicio3/alarme_residencial.v
module alarme_residencial(PORTA, JANELA, MOVIMENTO, SISTEMA, ALARME);

    input PORTA, JANELA, MOVIMENTO, SISTEMA;
    output ALARME;

    assign ALARME = MOVIMENTO | SISTEMA & (PORTA | JANELA);

endmodule

exercicio3/alarme_residencial_tb.v
`timescale 1ns/1ns
`include "alarme_residencial.v"

module alarme_residencial_tb;

    reg PORTA, JANELA, MOVIMENTO, SISTEMA;
    wire ALARME;
    alarme_residencial uut(PORTA, JANELA, MOVIMENTO, SISTEMA, ALARME);

    initial begin
        $dumpfile("alarme_residencial.vcd");
        $dumpvars(0, alarme_residencial_tb);

        PORTA = 0;
        JANELA = 0; 
        MOVIMENTO = 0;
        SISTEMA = 0;#20;

        PORTA = 0;
        JANELA = 0; 
        MOVIMENTO = 0;
        SISTEMA = 1;#20;

        PORTA = 0;
        JANELA = 0; 
        MOVIMENTO = 1;
        SISTEMA = 0;#20;

        PORTA = 0;
        JANELA = 0; 
        MOVIMENTO = 1;
        SISTEMA = 1;#20;

        PORTA = 0;
        JANELA = 1; 
        MOVIMENTO = 0;
        SISTEMA = 0;#20;

        PORTA = 0;
        JANELA = 1; 
        MOVIMENTO = 0;
        SISTEMA = 1;#20;

        PORTA = 0;
        JANELA = 1; 
        MOVIMENTO = 1;
        SISTEMA = 0;#20;

        PORTA = 0;
        JANELA = 1; 
        MOVIMENTO = 1;
        SISTEMA = 1;#20;

        PORTA = 1;
        JANELA = 0; 
        MOVIMENTO = 0;
        SISTEMA = 0;#20;

        PORTA = 1;
        JANELA = 0; 
        MOVIMENTO = 0;
        SISTEMA = 1;#20;

        PORTA = 1;
        JANELA = 0; 
        MOVIMENTO = 1;
        SISTEMA = 0;#20;

        PORTA = 1;
        JANELA = 0; 
        MOVIMENTO = 1;
        SISTEMA = 1;#20;

        PORTA = 1;
        JANELA = 1; 
        MOVIMENTO = 0;
        SISTEMA = 0;#20;

        PORTA = 1;
        JANELA = 1; 
        MOVIMENTO = 0;
        SISTEMA = 1;#20;

        PORTA = 1;
        JANELA = 1; 
        MOVIMENTO = 1;
        SISTEMA = 0;#20;

        PORTA = 1;
        JANELA = 1; 
        MOVIMENTO = 1;
        SISTEMA = 1;#20;

        $display("Teste completo");
    end

endmodule

ATIVIDADES-PRATICAS/ATIVIDADE-PRATICA-1/exercicio3/alarme_residencial.vcd
$date
	Sat Sep 07 02:46:06 2024
$end
$version
	Icarus Verilog
$end
$timescale
	1ns
$end
$scope module alarme_residencial_tb $end
$var wire 1 ! ALARME $end
$var reg 1 " JANELA $end
$var reg 1 # MOVIMENTO $end
$var reg 1 $ PORTA $end
$var reg 1 % SISTEMA $end
$scope module uut $end
$var wire 1 ! ALARME $end
$var wire 1 " JANELA $end
$var wire 1 # MOVIMENTO $end
$var wire 1 $ PORTA $end
$var wire 1 % SISTEMA $end
$upscope $end
$upscope $end
$enddefinitions $end
$comment Show the parameter values. $end
$dumpall
$end
#0
$dumpvars
0%
0$
0#
0"
0!
$end
#20
1%
#40
1!
0%
1#
#60
1%
#80
0!
0%
0#
1"
#100
1!
1%
#120
0%
1#
#140
1%
#160
0!
0%
0#
0"
1$
#180
1!
1%
#200
0%
1#
#220
1%
#240
0!
0%
0#
1"
#260
1!
1%
#280
0%
1#
#300
1%
