ATIVIDADES-PRATICAS/ATIVIDADE-PRATICA-5/flip-flop-d/ff_d.v
module ff_d (clk, d, preset, clear, q, qNot);

    input clk, d, preset, clear;
    output reg q, qNot; // Sempre usar reg quando o pino tiver dentro de um always

    /*
    2.) Desenvolva em Verilog um m´odulo que implemente um FF d com borda de descida e com PR
        e CLR ativos em nivel l´ogico alto (1). Anexe o c´odigo do m´odulo, o testbench e forma de onda
        no GTKWave.

        clear força para 0
        preset força para 1
    */

    always @(negedge clk) begin
        case ({preset, clear})
            2'b01: q = 0; // Preset = 0 Clear = 1 -> Clear ativo -> Q = 0
            2'b10: q = 1; // Preset = 1 Clear = 0 -> Preset ativo -> Q = 1
            2'b00: begin  // Preset = 0 Clear = 0 -> Funcionamento Normal do FFs
                if (d) q = 1;
                if (~d) q = 0;
            end
            default: q = 1'bX;// Preset = 1 Clear = 1 -> Clear ativo Preset ativo -> Q = X -> CASO INDEFINIDO
        endcase
        qNot = ~q;
    end

endmodule

ATIVIDADES-PRATICAS/ATIVIDADE-PRATICA-5/flip-flop-d/ff_d_tb.v
`timescale 1ns/1ns
`include "ff_d.v"

module ff_d_tb;

    reg clk, d, preset, clear;
    wire q, qNot;
    ff_d uut(clk, d, preset, clear, q, qNot);

    initial begin
        $dumpfile("ff_d.vcd");
        $dumpvars(0, ff_d_tb);

        {preset,clear,d} = 3'b000; #20;
        {preset,clear,d} = 3'b001; #20;
        {preset,clear,d} = 3'b010; #20;
        {preset,clear,d} = 3'b011; #20;
        {preset,clear,d} = 3'b100; #20;
        {preset,clear,d} = 3'b101; #20;
        {preset,clear,d} = 3'b110; #20;
        {preset,clear,d} = 3'b111; #20;

        $display("Teste completo");
        $finish;
    end

    initial begin
        clk = 0;
        forever #10 clk = ~clk ;
    end

endmodule

ATIVIDADES-PRATICAS/ATIVIDADE-PRATICA-5/flip-flop-d/ff_d.vcd
$date
	Sat Nov 02 00:48:29 2024
$end
$version
	Icarus Verilog
$end
$timescale
	1ns
$end
$scope module ff_d_tb $end
$var wire 1 ! qNot $end
$var wire 1 " q $end
$var reg 1 # clear $end
$var reg 1 $ clk $end
$var reg 1 % d $end
$var reg 1 & preset $end
$scope module uut $end
$var wire 1 # clear $end
$var wire 1 $ clk $end
$var wire 1 % d $end
$var wire 1 & preset $end
$var reg 1 " q $end
$var reg 1 ! qNot $end
$upscope $end
$upscope $end
$enddefinitions $end
$comment Show the parameter values. $end
$dumpall
$end
#0
$dumpvars
0&
0%
0$
0#
0"
1!
$end
#10
1$
#20
0!
1"
0$
1%
#30
1$
#40
1!
0"
0$
1#
0%
#50
1$
#60
0$
1%
#70
1$
#80
0!
1"
0$
1&
0#
0%
#90
1$
#100
0$
1%
#110
1$
#120
x!
x"
0$
1#
0%
#130
1$
#140
0$
1%
