ATIVIDADES-PRATICAS/ATIVIDADE-PRATICA-4/somador e subtrator de n bits/somador/somador_completo.v
module somador_completo (A, B, CIN, S, COUT);

    input A, B, CIN;
    output S, COUT;

    assign S = A ^ B ^ CIN; 
    assign COUT = B & CIN | A & CIN | A & B;

endmodule

ATIVIDADES-PRATICAS/ATIVIDADE-PRATICA-4/somador/completo/somador_completo_tb.v
`timescale 1ns/1ns
`include "somador_completo.v"

module somador_completo_tb;

    reg A, B, CIN;
    wire S, COUT;

    somador_completo uut(A, B, CIN, S, COUT);

    initial begin
        $dumpfile("somador_completo.vcd");
        $dumpvars(0, somador_completo_tb);

        A = 0;
        B = 0;
        CIN = 0;#20;

        A = 0;
        B = 0;
        CIN = 1;#20;

        A = 0;
        B = 1;
        CIN = 0;#20;

        A = 0;
        B = 1;
        CIN = 1;#20;
        
        A = 1;
        B = 0;
        CIN = 0;#20;

        A = 1;
        B = 0;
        CIN = 1;#20;

        A = 1;
        B = 1;
        CIN = 0;#20;

        A = 1;
        B = 1;
        CIN = 1;#20;

        $display("Teste completo");
    end

endmodule

ATIVIDADES-PRATICAS/ATIVIDADE-PRATICA-4/somador/completo/somador_completo.vcd
$date
	Fri Sep 27 09:57:17 2024
$end
$version
	Icarus Verilog
$end
$timescale
	1ns
$end
$scope module somador_completo_tb $end
$var wire 1 ! S $end
$var wire 1 " COUT $end
$var reg 1 # A $end
$var reg 1 $ B $end
$var reg 1 % CIN $end
$scope module uut $end
$var wire 1 # A $end
$var wire 1 $ B $end
$var wire 1 % CIN $end
$var wire 1 " COUT $end
$var wire 1 ! S $end
$upscope $end
$upscope $end
$enddefinitions $end
$comment Show the parameter values. $end
$dumpall
$end
#0
$dumpvars
0%
0$
0#
0"
0!
$end
#20
1!
1%
#40
0%
1$
#60
1"
0!
1%
#80
0"
1!
0%
0$
1#
#100
1"
0!
1%
#120
0%
1$
#140
1!
1%
