ATIVIDADES-PRATICAS/ATIVIDADE-PRATICA-5/flip-flop-jk/ff_jk.v
module ff_jk (clk, j, k, preset, clear, q, qNot);

    input wire clk, j, k, preset, clear;
    output reg q;
    output wire qNot;

    assign qNot = ~q;

    always @(posedge clk) begin
        
        if (preset && clear)
            case ({j, k})
                2'b00:
                    q = q;
                2'b01:
                    q = 0;
                2'b10:
                    q = 1;
                2'b11:
                    q = ~q;
            endcase
        else
            case ({preset, clear})
                2'b10: 
                    q = 0; 
                2'b01: 
                    q = 1; 
                2'b00: 
                    q = 1'bX; 
            endcase
    end

endmodule

ATIVIDADES-PRATICAS/ATIVIDADE-PRATICA-5/flip-flop-jk/ff_jk_tb.v
`timescale 1ns/1ns
`include "ff_jk.v"

module ff_jk_tb;

    reg clk, j, k, preset, clear;
    wire q, qNot;
    ff_jk uut(clk, j, k, preset, clear, q, qNot);

    initial begin
        $dumpfile("ff_jk.vcd");
        $dumpvars(0, ff_jk_tb);

        {j, k, preset, clear} = 4'b0000; #20;
        {j, k, preset, clear} = 4'b0001; #20;
        {j, k, preset, clear} = 4'b0010; #20;
        {j, k, preset, clear} = 4'b0011; #20;
        {j, k, preset, clear} = 4'b0100; #20;
        {j, k, preset, clear} = 4'b0101; #20;
        {j, k, preset, clear} = 4'b0110; #20;
        {j, k, preset, clear} = 4'b0111; #20;
        {j, k, preset, clear} = 4'b1000; #20;
        {j, k, preset, clear} = 4'b1001; #20;
        {j, k, preset, clear} = 4'b1010; #20;
        {j, k, preset, clear} = 4'b1011; #20;
        {j, k, preset, clear} = 4'b1100; #20;
        {j, k, preset, clear} = 4'b1101; #20;
        {j, k, preset, clear} = 4'b1110; #20;
        {j, k, preset, clear} = 4'b1111; #20;

        $display("Teste completo");
        $finish;
    end

    initial begin
        clk = 0;
        forever #10 clk = ~clk ;
    end

endmodule

ATIVIDADES-PRATICAS/ATIVIDADE-PRATICA-5/flip-flop-jk/ff_jk.vcd
$date
	Fri Nov 01 23:40:54 2024
$end
$version
	Icarus Verilog
$end
$timescale
	1ns
$end
$scope module ff_jk_tb $end
$var wire 1 ! qNot $end
$var wire 1 " q $end
$var reg 1 # clear $end
$var reg 1 $ clk $end
$var reg 1 % j $end
$var reg 1 & k $end
$var reg 1 ' preset $end
$scope module uut $end
$var wire 1 # clear $end
$var wire 1 $ clk $end
$var wire 1 % j $end
$var wire 1 & k $end
$var wire 1 ' preset $end
$var wire 1 ! qNot $end
$var reg 1 " q $end
$upscope $end
$upscope $end
$enddefinitions $end
$comment Show the parameter values. $end
$dumpall
$end
#0
$dumpvars
0'
0&
0%
0$
0#
x"
x!
$end
#10
1$
#20
0$
1#
#30
0!
1"
1$
#40
0$
1'
0#
#50
1!
0"
1$
#60
0$
1#
#70
1$
#80
0$
1&
0'
0#
#90
x!
x"
1$
#100
0$
1#
#110
0!
1"
1$
#120
0$
1'
0#
#130
1!
0"
1$
#140
0$
1#
#150
1$
#160
0$
1%
0&
0'
0#
#170
x!
x"
1$
#180
0$
1#
#190
0!
1"
1$
#200
0$
1'
0#
#210
1!
0"
1$
#220
0$
1#
#230
0!
1"
1$
#240
0$
1&
0'
0#
#250
x!
x"
1$
#260
0$
1#
#270
0!
1"
1$
#280
0$
1'
0#
#290
1!
0"
1$
#300
0$
1#
#310
0!
1"
1$
