ATIVIDADES-PRATICAS/ATIVIDADE-PRATICA-7/morse.v
module morse (in, out, reset, clk);

    input in, reset, clk;
    output reg [7:0] out;

    parameter A = 5'b00001, B = 5'b00010, C = 5'b00011, D = 5'b00100, E = 5'b00101, 
              F = 5'b00110, G = 5'b00111, H = 5'b01000, I = 5'b01001, J = 5'b01010,
              K = 5'b01011, L = 5'b01100, M = 5'b01101, N = 5'b01110, O = 5'b01111,
              P = 5'b10000, Q = 5'b10001, R = 5'b10010, S = 5'b10011, T = 5'b10100,
              U = 5'b10101, V = 5'b10110, W = 5'b10111, X = 5'b11000, Y = 5'b11001,
              Z = 5'b11010, IDLE = 5'bxxxxx;

    reg [5:0] state, next_state;

    // Lógica Sequencial    
    always @(posedge clk) begin
        if (reset)
            state = IDLE;
        else
            state = next_state;        
    end
    
    // Lógica Combinacional de entrada
    always @(*) begin
        case (state)   // 1 -> ponto 0 -> traço
            IDLE: begin
                if (in)
                    next_state = E; // .
                else
                    next_state = T; // -
            end   
            E: begin
                if (in)
                    next_state = I; // ..
                else
                    next_state = A; // .-
            end
            A: begin
                if (in)
                    next_state = R; // .-.
                else
                    next_state = W; // .--
            end
            R: begin
                if (in)
                    next_state = L; // .-..
                else
                    next_state = IDLE;
            end
            W: begin
                if (in)
                    next_state = P; // .--.
                else
                    next_state = J; // .---
            end
            I: begin
                if (in)
                    next_state = S; // ...
                else 
                    next_state = U; // ..-
            end 
            S: begin
                if (in)
                    next_state = H; // ....
                else
                    next_state = V; // ...-
            end
            U: begin
                if (in) 
                    next_state = F; //..-.
                else 
                    next_state = IDLE;
            end
            T: begin
                if (in)
                    next_state = N; // -.
                else
                    next_state = M; // --
            end
            M: begin
                if (in)
                    next_state = G; // --.
                else
                    next_state = O; // ---
            end
            G: begin
                if (in)
                    next_state = Z; // --..
                else
                    next_state = Q; // --.-
            end
            N: begin
                if (in)
                    next_state = D; // -..
                else
                    next_state = K; // -.-
            end
            D: begin
                if (in)
                    next_state = B; // -...
                else
                    next_state = X; // -..-
            end
            K: begin
                if (in)
                    next_state = C; // -.-.
                else 
                    next_state = Y; // -.--
            end
                             
            default: next_state = IDLE;
        endcase
        
    end

    // Lógica Combinacional de saída
    always @(*) begin
        case (state)
            IDLE: out = 8'h00;
            A: out = 8'h41; 
            B: out = 8'h42; 
            C: out = 8'h43;
            D: out = 8'h44;
            E: out = 8'h45;
            F: out = 8'h46;
            G: out = 8'h47;
            H: out = 8'h48;
            I: out = 8'h49;
            J: out = 8'h4A;
            K: out = 8'h4B;
            L: out = 8'h4C;
            M: out = 8'h4D;
            N: out = 8'h4E;
            O: out = 8'h4F;
            P: out = 8'h50;
            Q: out = 8'h51;
            R: out = 8'h52;
            S: out = 8'h53;
            T: out = 8'h54;
            U: out = 8'h55;
            V: out = 8'h56;
            W: out = 8'h57;
            X: out = 8'h58;
            Y: out = 8'h59;
            Z: out = 8'h5A;
            default: next_state = IDLE;
        endcase
    end
endmodule

ATIVIDADES-PRATICAS/ATIVIDADE-PRATICA-7/morse_tb.v
`timescale 10ns/1ns
`include "morse.v"

module morse_tb;


    reg in, reset, clk;
    wire [7:0] out;
    morse uut(in, out, reset, clk);

    initial begin
        $dumpfile("morse.vcd");
        $dumpvars(0, morse_tb);

        in = 1;
        // TESTE DE TODAS AS LETRAS EM SEQUENCIA

        // LETRA A
        reset = 1; #10
        reset = 0; #10
        in = 1; #10     // .
        in = 0; #10 #10 // -

        // LETRA B
        reset = 1; #10 #10
        reset = 0; #10 #10
        in = 0; #10// -
        in = 1; #10 #10 // .
        #10 #10 // .
        #10 #10 // .

        // LETRA C
        in = 0; // -
        reset = 1; #10 #10
        reset = 0; #10 #10
        in = 1; #10 // .
        in = 0; #10 #10// -
        in = 1; #10 #10 // .

        #10
        $finish;
    end

    initial begin
        clk = 1;
        forever #10 clk = ~clk;
    end
    

endmodule

ATIVIDADES-PRATICAS/ATIVIDADE-PRATICA-7/morse.vcd
$date
	Mon Nov 25 02:14:55 2024
$end
$version
	Icarus Verilog
$end
$timescale
	1ns
$end
$scope module morse_tb $end
$var wire 8 ! out [7:0] $end
$var reg 1 " clk $end
$var reg 1 # in $end
$var reg 1 $ reset $end
$scope module uut $end
$var wire 1 " clk $end
$var wire 1 # in $end
$var wire 1 $ reset $end
$var parameter 5 % A $end
$var parameter 5 & B $end
$var parameter 5 ' C $end
$var parameter 5 ( D $end
$var parameter 5 ) E $end
$var parameter 5 * F $end
$var parameter 5 + G $end
$var parameter 5 , H $end
$var parameter 5 - I $end
$var parameter 5 . IDLE $end
$var parameter 5 / J $end
$var parameter 5 0 K $end
$var parameter 5 1 L $end
$var parameter 5 2 M $end
$var parameter 5 3 N $end
$var parameter 5 4 O $end
$var parameter 5 5 P $end
$var parameter 5 6 Q $end
$var parameter 5 7 R $end
$var parameter 5 8 S $end
$var parameter 5 9 T $end
$var parameter 5 : U $end
$var parameter 5 ; V $end
$var parameter 5 < W $end
$var parameter 5 = X $end
$var parameter 5 > Y $end
$var parameter 5 ? Z $end
$var reg 6 @ next_state [5:0] $end
$var reg 8 A out [7:0] $end
$var reg 6 B state [5:0] $end
$upscope $end
$upscope $end
$enddefinitions $end
$comment Show the parameter values. $end
$dumpall
b11010 ?
b11001 >
b11000 =
b10111 <
b10110 ;
b10101 :
b10100 9
b10011 8
b10010 7
b10001 6
b10000 5
b1111 4
b1110 3
b1101 2
b1100 1
b1011 0
b1010 /
bx .
b1001 -
b1000 ,
b111 +
b110 *
b101 )
b100 (
b11 '
b10 &
b1 %
$end
#0
$dumpvars
b0xxxxx B
b0 A
b101 @
1$
1#
1"
b0 !
$end
#100
0"
0$
#200
b1000101 !
b1000101 A
b1001 @
b101 B
1"
#300
b1 @
0"
0#
#400
b1000001 !
b1000001 A
b10111 @
b1 B
1"
#500
0"
1$
#600
b0 !
b0 A
b10100 @
b0xxxxx B
1"
#700
0"
0$
#800
b1010100 !
b1010100 A
b1101 @
b10100 B
1"
#900
0"
#1000
b1001110 !
b1001110 A
b1110 B
b100 @
1"
1#
#1100
0"
#1200
b1000100 !
b1000100 A
b10 @
b100 B
1"
#1300
0"
#1400
b1000010 !
b1000010 A
b0xxxxx @
b10 B
1"
#1500
0"
#1600
b0 !
b0 A
b10100 @
b0xxxxx B
1"
1$
0#
#1700
0"
#1800
b1010100 !
b1010100 A
b1101 @
b10100 B
1"
0$
#1900
0"
#2000
b1001110 !
b1001110 A
b1110 B
b100 @
1"
1#
#2100
b1011 @
0"
0#
#2200
b1001011 !
b1001011 A
b11001 @
b1011 B
1"
#2300
b11 @
0"
1#
#2400
b1000011 !
b1000011 A
b0xxxxx @
b11 B
1"
#2500
0"
#2600
b0 !
b0 A
b101 @
b0xxxxx B
1"
