ATIVIDADES-PRATICAS/ATIVIDADE-PRATICA-1/exercicio2/fila_prioridade.v
module fila_prioridade(TV, PC, Alexa, s1, s2, s3);

    input TV, PC, Alexa;
    output s1, s2, s3;

    assign s1 = TV;
    assign s2 = ~TV & PC;
    assign s3 = ~TV & ~PC & Alexa;

endmodule

exercicio2/fila_prioridade_tb.v
`timescale 1ns/1ns
`include "fila_prioridade.v"

module fila_prioridade_tb;

    reg TV, PC, Alexa;
    wire s1, s2, s3;
    fila_prioridade uut(TV, PC, Alexa, s1, s2, s3);

    initial begin
        $dumpfile("fila_prioridade.vcd");
        $dumpvars(0, fila_prioridade_tb);

        TV = 0;
        PC = 0; 
        Alexa = 0;#20;

        TV = 0;
        PC = 0; 
        Alexa = 1;#20;

        TV = 0;
        PC = 1; 
        Alexa = 0;#20;

        TV = 0;
        PC = 1; 
        Alexa = 1;#20;

        TV = 1;
        PC = 0; 
        Alexa = 0;#20;

        TV = 1;
        PC = 0; 
        Alexa = 1;#20;

        TV = 1;
        PC = 1; 
        Alexa = 0;#20;

        TV = 1;
        PC = 1; 
        Alexa = 1;#20;

        $display("Teste completo");
    end

endmodule

ATIVIDADES-PRATICAS/ATIVIDADE-PRATICA-1/exercicio2/fila_prioridade.vcd
$date
	Fri Sep 06 11:31:59 2024
$end
$version
	Icarus Verilog
$end
$timescale
	1ns
$end
$scope module fila_prioridade_tb $end
$var wire 1 ! s3 $end
$var wire 1 " s2 $end
$var wire 1 # s1 $end
$var reg 1 $ Alexa $end
$var reg 1 % PC $end
$var reg 1 & TV $end
$scope module uut $end
$var wire 1 $ Alexa $end
$var wire 1 % PC $end
$var wire 1 & TV $end
$var wire 1 # s1 $end
$var wire 1 " s2 $end
$var wire 1 ! s3 $end
$upscope $end
$upscope $end
$enddefinitions $end
$comment Show the parameter values. $end
$dumpall
$end
#0
$dumpvars
0&
0%
0$
0#
0"
0!
$end
#20
1!
1$
#40
0!
1"
0$
1%
#60
1$
#80
0"
0$
0%
1#
1&
#100
1$
#120
0$
1%
#140
1$
