ATIVIDADES-PRATICAS/ATIVIDADE-PRATICA-5/flip-flop-d/ff_d.v
module ff_d (clk, d, preset, clear, q, qNot);

    input clk, d, preset, clear;
    output reg q, qNot; // Sempre usar reg quando o pino tiver dentro de um always

    /*
    2.) Desenvolva em Verilog um m´odulo que implemente um FF d com borda de descida e com PR
        e CLR ativos em nivel l´ogico alto (1). Anexe o c´odigo do m´odulo, o testbench e forma de onda
        no GTKWave.

        clear força para 0
        preset força para 1
    */

    always @(negedge clk) begin
        case ({preset, clear})
            2'b01: q = 0; // Preset = 0 Clear = 1 -> Clear ativo -> Q = 0
            2'b10: q = 1; // Preset = 1 Clear = 0 -> Preset ativo -> Q = 1
            2'b00: begin  // Preset = 0 Clear = 0 -> Funcionamento Normal do FFs
                if (d) q = 1;
                if (~d) q = 0;
            end
            default: q = 1'bX;// Preset = 1 Clear = 1 -> Clear ativo Preset ativo -> Q = X -> CASO INDEFINIDO
        endcase
        qNot = ~q;
    end

endmodule

ATIVIDADES-PRATICAS/ATIVIDADE-PRATICA-5/registrador-8bits-ff-d/registrador_8bits.v
`include "ff_d.v"

module registrador_8bits (clk, d, preset, clear, q, qneg);

    input [7:0] d;
    output [7:0] q, qneg;

    input clk, preset, clear;

    ff_d ff1 (clk, d[0], preset, clear, q[0], qneg[0]);
    ff_d ff2 (clk, d[1], preset, clear, q[1], qneg[1]);
    ff_d ff3 (clk, d[2], preset, clear, q[2], qneg[2]);
    ff_d ff4 (clk, d[3], preset, clear, q[3], qneg[3]);
    ff_d ff5 (clk, d[4], preset, clear, q[4], qneg[4]);
    ff_d ff6 (clk, d[5], preset, clear, q[5], qneg[5]);
    ff_d ff7 (clk, d[6], preset, clear, q[6], qneg[6]);
    ff_d ff8 (clk, d[7], preset, clear, q[7], qneg[7]);

endmodule

ATIVIDADES-PRATICAS/ATIVIDADE-PRATICA-5/registrador-8bits-ff-d/registrador_8bits_tb.v
`timescale 1ns/1ns
`include "registrador_8bits.v"

module registrador_8bits_tb;

    reg [7:0] d;
    wire [7:0] q, qneg;

    reg clk, preset, clear;

    registrador_8bits uut(clk, d, preset, clear, q, qneg);

    initial begin
        $dumpfile("registrador_8bits.vcd");
        $dumpvars(0, registrador_8bits_tb);

        // Teste: Clear e Preset desativados
        preset = 0; clear = 0; d = 8'b00000000; #20;
        d = 8'b11111111; #20;
        d = 8'b10101010; #20;

        // Teste: Preset ativo, Clear inativo
        preset = 1; clear = 0; d = 8'b00000000; #20;
        d = 8'b11111111; #20;
        d = 8'b01010101; #20;

        // Teste: Clear ativo, Preset inativo
        preset = 0; clear = 1; d = 8'b00000000; #20;
        d = 8'b11111111; #20;
        d = 8'b00110011; #20;

        // Teste: Clear e Preset ambos ativos
        preset = 1; clear = 1; d = 8'b00000000; #20;
        d = 8'b11111111; #20;

        $display("Teste completo");
        $finish;
    end

    initial begin
        clk = 0;
        forever #10 clk = ~clk ;
    end

endmodule

ATIVIDADES-PRATICAS/ATIVIDADE-PRATICA-5/registrador-8bits-ff-d/registrador_8bits.vcd
$date
	Sat Nov 02 23:04:20 2024
$end
$version
	Icarus Verilog
$end
$timescale
	1ns
$end
$scope module registrador_8bits_tb $end
$var wire 8 ! qneg [7:0] $end
$var wire 8 " q [7:0] $end
$var reg 1 # clear $end
$var reg 1 $ clk $end
$var reg 8 % d [7:0] $end
$var reg 1 & preset $end
$scope module uut $end
$var wire 1 # clear $end
$var wire 1 $ clk $end
$var wire 8 ' d [7:0] $end
$var wire 1 & preset $end
$var wire 8 ( qneg [7:0] $end
$var wire 8 ) q [7:0] $end
$scope module ff1 $end
$var wire 1 # clear $end
$var wire 1 $ clk $end
$var wire 1 * d $end
$var wire 1 & preset $end
$var reg 1 + q $end
$var reg 1 , qNot $end
$upscope $end
$scope module ff2 $end
$var wire 1 # clear $end
$var wire 1 $ clk $end
$var wire 1 - d $end
$var wire 1 & preset $end
$var reg 1 . q $end
$var reg 1 / qNot $end
$upscope $end
$scope module ff3 $end
$var wire 1 # clear $end
$var wire 1 $ clk $end
$var wire 1 0 d $end
$var wire 1 & preset $end
$var reg 1 1 q $end
$var reg 1 2 qNot $end
$upscope $end
$scope module ff4 $end
$var wire 1 # clear $end
$var wire 1 $ clk $end
$var wire 1 3 d $end
$var wire 1 & preset $end
$var reg 1 4 q $end
$var reg 1 5 qNot $end
$upscope $end
$scope module ff5 $end
$var wire 1 # clear $end
$var wire 1 $ clk $end
$var wire 1 6 d $end
$var wire 1 & preset $end
$var reg 1 7 q $end
$var reg 1 8 qNot $end
$upscope $end
$scope module ff6 $end
$var wire 1 # clear $end
$var wire 1 $ clk $end
$var wire 1 9 d $end
$var wire 1 & preset $end
$var reg 1 : q $end
$var reg 1 ; qNot $end
$upscope $end
$scope module ff7 $end
$var wire 1 # clear $end
$var wire 1 $ clk $end
$var wire 1 < d $end
$var wire 1 & preset $end
$var reg 1 = q $end
$var reg 1 > qNot $end
$upscope $end
$scope module ff8 $end
$var wire 1 # clear $end
$var wire 1 $ clk $end
$var wire 1 ? d $end
$var wire 1 & preset $end
$var reg 1 @ q $end
$var reg 1 A qNot $end
$upscope $end
$upscope $end
$upscope $end
$enddefinitions $end
$comment Show the parameter values. $end
$dumpall
$end
#0
$dumpvars
1A
0@
0?
1>
0=
0<
1;
0:
09
18
07
06
15
04
03
12
01
00
1/
0.
0-
1,
0+
0*
b0 )
b11111111 (
b0 '
0&
b0 %
0$
0#
b0 "
b11111111 !
$end
#10
1$
#20
0A
1@
0>
1=
0;
1:
08
17
05
14
02
11
0/
1.
b0 !
b0 (
0,
b11111111 "
b11111111 )
1+
1*
1-
10
13
16
19
1<
1?
0$
b11111111 %
b11111111 '
#30
1$
#40
1,
0+
12
01
18
07
b1010101 !
b1010101 (
1>
b10101010 "
b10101010 )
0=
0*
00
06
0<
0$
b10101010 %
b10101010 '
#50
1$
#60
0>
1=
08
17
02
11
b0 !
b0 (
0,
b11111111 "
b11111111 )
1+
0-
03
09
0?
0$
b0 %
b0 '
1&
#70
1$
#80
1*
1-
10
13
16
19
1<
1?
0$
b11111111 %
b11111111 '
#90
1$
#100
0-
03
09
0?
0$
b1010101 %
b1010101 '
#110
1$
#120
1,
0+
1/
0.
12
01
15
04
18
07
1;
0:
1>
0=
b11111111 !
b11111111 (
1A
b0 "
b0 )
0@
0*
00
06
0<
0$
b0 %
b0 '
1#
0&
#130
1$
#140
1*
1-
10
13
16
19
1<
1?
0$
b11111111 %
b11111111 '
#150
1$
#160
00
03
0<
0?
0$
b110011 %
b110011 '
#170
1$
#180
xA
x@
x>
x=
x;
x:
x8
x7
x5
x4
x2
x1
x/
x.
bx !
bx (
x,
bx "
bx )
x+
0*
0-
06
09
0$
b0 %
b0 '
1&
#190
1$
#200
1*
1-
10
13
16
19
1<
1?
0$
b11111111 %
b11111111 '
